{
  "gridSize": 6,
  "title": "Indian Mini Crossword - 2025-08-02",
  "words": [
    {
      "id": 3,
      "orientation": "DOWN",
      "start": {
        "row": 0,
        "col": 2
      },
      "length": 5,
      "answer": "SARIS",
      "clue": "Traditional Indian attire wraps.",
      "startPosition": {
        "row": 0,
        "col": 2
      }
    },
    {
      "id": 5,
      "orientation": "DOWN",
      "start": {
        "row": 1,
        "col": 3
      },
      "length": 5,
      "answer": "DELHI",
      "clue": "India's bustling capital city.",
      "startPosition": {
        "row": 1,
        "col": 3
      }
    },
    {
      "id": 2,
      "orientation": "DOWN",
      "start": {
        "row": 0,
        "col": 1
      },
      "length": 4,
      "answer": "YOGA",
      "clue": "Ancient Indian practice for body and mind.",
      "startPosition": {
        "row": 0,
        "col": 1
      }
    },
    {
      "id": 4,
      "orientation": "ACROSS",
      "start": {
        "row": 1,
        "col": 0
      },
      "length": 4,
      "answer": "TOAD",
      "clue": "Amphibian often found near Indian ponds.",
      "startPosition": {
        "row": 1,
        "col": 0
      }
    },
    {
      "id": 6,
      "orientation": "ACROSS",
      "start": {
        "row": 2,
        "col": 1
      },
      "length": 4,
      "answer": "GREY",
      "clue": "A color often seen in monsoon skies.",
      "startPosition": {
        "row": 2,
        "col": 1
      }
    },
    {
      "id": 7,
      "orientation": "DOWN",
      "start": {
        "row": 2,
        "col": 4
      },
      "length": 4,
      "answer": "YARN",
      "clue": "Spun thread or a tale told over chai.",
      "startPosition": {
        "row": 2,
        "col": 4
      }
    },
    {
      "id": 8,
      "orientation": "ACROSS",
      "start": {
        "row": 3,
        "col": 1
      },
      "length": 4,
      "answer": "AILA",
      "clue": "A traditional alcoholic beverage from the Newar community in Nepal and parts of India.",
      "startPosition": {
        "row": 3,
        "col": 1
      }
    },
    {
      "id": 9,
      "orientation": "ACROSS",
      "start": {
        "row": 4,
        "col": 2
      },
      "length": 4,
      "answer": "SHRI",
      "clue": "A respectful title used in India, often before men's names.",
      "startPosition": {
        "row": 4,
        "col": 2
      }
    },
    {
      "id": 1,
      "orientation": "ACROSS",
      "start": {
        "row": 0,
        "col": 0
      },
      "length": 3,
      "answer": "BYS",
      "clue": "Like bylaws, but shorter and neater.",
      "startPosition": {
        "row": 0,
        "col": 0
      }
    },
    {
      "id": 10,
      "orientation": "ACROSS",
      "start": {
        "row": 5,
        "col": 3
      },
      "length": 3,
      "answer": "INK",
      "clue": "This liquid leaves a mark; essential for writers.",
      "startPosition": {
        "row": 5,
        "col": 3
      }
    }
  ],
  "solutionGrid": [
    [
      "B",
      "Y",
      "S",
      null,
      null,
      null
    ],
    [
      "T",
      "O",
      "A",
      "D",
      null,
      null
    ],
    [
      null,
      "G",
      "R",
      "E",
      "Y",
      null
    ],
    [
      null,
      "A",
      "I",
      "L",
      "A",
      null
    ],
    [
      null,
      null,
      "S",
      "H",
      "R",
      "I"
    ],
    [
      null,
      null,
      null,
      "I",
      "N",
      "K"
    ]
  ]
}